graphcat/__init__.py
graphcat/common.py
graphcat/diagram.py
graphcat/dynamic.py
graphcat/graph.py
graphcat/notebook.py
graphcat/optional.py
graphcat/require.py
graphcat/static.py
graphcat/streaming.py
graphcat-1.0.5.dist-info/LICENSE
graphcat-1.0.5.dist-info/WHEEL
graphcat-1.0.5.dist-info/METADATA
graphcat-1.0.5.dist-info/RECORD
